afstest-0.1.0.dist-info/METADATA
afstest-0.1.0.dist-info/WHEEL
afstest-0.1.0.dist-info/entry_points.txt
afstest/__init__.py
afstest/_select.py
afstest/cli.py
afstest/webui_frame/commons/kdt.py
afstest/webui_frame/conftest.py
afstest/webui_frame/main.py
afstest/webui_frame/pytest.ini
afstest/webui_frame/requirements.txt
afstest/webui_frame/tests/test_baidu.py
afstest/webui_frame/tests/test_conv.xlsx
afstest-0.1.0.dist-info/RECORD
