Metadata-Version: 2.1
Name: afstest
Version: 0.1.0
Summary: autotest init tools.
Author-Email: funcdefmain <741132517@qq.com>
License: MIT
Requires-Python: >=3.10
